{
  "schema_version": "daily_prices_v1",
  "ticker": "GS",
  "year": 2023,
  "quarter": "Q2",
  "start_date": "2023-04-03",
  "end_date": "2023-06-30",
  "trading_days": 62,
  "daily_close": [
    {
      "date": "2023-04-03",
      "close": 303.3954
    },
    {
      "date": "2023-04-04",
      "close": 299.7995
    },
    {
      "date": "2023-04-05",
      "close": 298.7589
    },
    {
      "date": "2023-04-06",
      "close": 299.5672
    },
    {
      "date": "2023-04-10",
      "close": 301.9459
    },
    {
      "date": "2023-04-11",
      "close": 304.1852
    },
    {
      "date": "2023-04-12",
      "close": 306.852
    },
    {
      "date": "2023-04-13",
      "close": 308.6082
    },
    {
      "date": "2023-04-14",
      "close": 313.0589
    },
    {
      "date": "2023-04-17",
      "close": 315.6234
    },
    {
      "date": "2023-04-18",
      "close": 310.2621
    },
    {
      "date": "2023-04-19",
      "close": 313.0311
    },
    {
      "date": "2023-04-20",
      "close": 314.7221
    },
    {
      "date": "2023-04-21",
      "close": 317.4632
    },
    {
      "date": "2023-04-24",
      "close": 319.6003
    },
    {
      "date": "2023-04-25",
      "close": 315.4376
    },
    {
      "date": "2023-04-26",
      "close": 312.7245
    },
    {
      "date": "2023-04-27",
      "close": 317.4075
    },
    {
      "date": "2023-04-28",
      "close": 319.1171
    },
    {
      "date": "2023-05-01",
      "close": 316.4504
    },
    {
      "date": "2023-05-02",
      "close": 309.7603
    },
    {
      "date": "2023-05-03",
      "close": 305.3746
    },
    {
      "date": "2023-05-04",
      "close": 298.508
    },
    {
      "date": "2023-05-05",
      "close": 303.86
    },
    {
      "date": "2023-05-08",
      "close": 303.3862
    },
    {
      "date": "2023-05-09",
      "close": 301.7694
    },
    {
      "date": "2023-05-10",
      "close": 299.7066
    },
    {
      "date": "2023-05-11",
      "close": 298.0062
    },
    {
      "date": "2023-05-12",
      "close": 296.8727
    },
    {
      "date": "2023-05-15",
      "close": 299.2606
    },
    {
      "date": "2023-05-16",
      "close": 298.0899
    },
    {
      "date": "2023-05-17",
      "close": 306.7963
    },
    {
      "date": "2023-05-18",
      "close": 306.2387
    },
    {
      "date": "2023-05-19",
      "close": 303.0517
    },
    {
      "date": "2023-05-22",
      "close": 301.9088
    },
    {
      "date": "2023-05-23",
      "close": 300.6544
    },
    {
      "date": "2023-05-24",
      "close": 297.1606
    },
    {
      "date": "2023-05-25",
      "close": 300.9424
    },
    {
      "date": "2023-05-26",
      "close": 308.4966
    },
    {
      "date": "2023-05-30",
      "close": 307.4002
    },
    {
      "date": "2023-05-31",
      "close": 303.2526
    },
    {
      "date": "2023-06-01",
      "close": 296.2307
    },
    {
      "date": "2023-06-02",
      "close": 303.0186
    },
    {
      "date": "2023-06-05",
      "close": 301.2958
    },
    {
      "date": "2023-06-06",
      "close": 305.9677
    },
    {
      "date": "2023-06-07",
      "close": 314.3472
    },
    {
      "date": "2023-06-08",
      "close": 314.0851
    },
    {
      "date": "2023-06-09",
      "close": 314.6
    },
    {
      "date": "2023-06-12",
      "close": 317.8488
    },
    {
      "date": "2023-06-13",
      "close": 320.6669
    },
    {
      "date": "2023-06-14",
      "close": 316.847
    },
    {
      "date": "2023-06-15",
      "close": 318.0829
    },
    {
      "date": "2023-06-16",
      "close": 316.744
    },
    {
      "date": "2023-06-20",
      "close": 309.6379
    },
    {
      "date": "2023-06-21",
      "close": 304.3481
    },
    {
      "date": "2023-06-22",
      "close": 299.2079
    },
    {
      "date": "2023-06-23",
      "close": 294.6484
    },
    {
      "date": "2023-06-26",
      "close": 292.4482
    },
    {
      "date": "2023-06-27",
      "close": 293.4688
    },
    {
      "date": "2023-06-28",
      "close": 293.6654
    },
    {
      "date": "2023-06-29",
      "close": 302.4943
    },
    {
      "date": "2023-06-30",
      "close": 301.9793
    }
  ]
}