{
  "schema_version": "daily_prices_v1",
  "ticker": "META",
  "year": 2024,
  "quarter": "Q1",
  "start_date": "2024-01-02",
  "end_date": "2024-03-28",
  "trading_days": 61,
  "daily_close": [
    {
      "date": "2024-01-02",
      "close": 343.8878
    },
    {
      "date": "2024-01-03",
      "close": 342.0804
    },
    {
      "date": "2024-01-04",
      "close": 344.7121
    },
    {
      "date": "2024-01-05",
      "close": 349.5086
    },
    {
      "date": "2024-01-08",
      "close": 356.172
    },
    {
      "date": "2024-01-09",
      "close": 354.9505
    },
    {
      "date": "2024-01-10",
      "close": 367.9001
    },
    {
      "date": "2024-01-11",
      "close": 367.1057
    },
    {
      "date": "2024-01-12",
      "close": 371.8922
    },
    {
      "date": "2024-01-16",
      "close": 364.9109
    },
    {
      "date": "2024-01-17",
      "close": 365.8147
    },
    {
      "date": "2024-01-18",
      "close": 373.5208
    },
    {
      "date": "2024-01-19",
      "close": 380.79
    },
    {
      "date": "2024-01-22",
      "close": 379.1316
    },
    {
      "date": "2024-01-23",
      "close": 382.5279
    },
    {
      "date": "2024-01-24",
      "close": 387.9898
    },
    {
      "date": "2024-01-25",
      "close": 390.4526
    },
    {
      "date": "2024-01-26",
      "close": 391.4059
    },
    {
      "date": "2024-01-29",
      "close": 398.2382
    },
    {
      "date": "2024-01-30",
      "close": 397.2848
    },
    {
      "date": "2024-01-31",
      "close": 387.4336
    },
    {
      "date": "2024-02-01",
      "close": 392.0414
    },
    {
      "date": "2024-02-02",
      "close": 471.695
    },
    {
      "date": "2024-02-05",
      "close": 456.2231
    },
    {
      "date": "2024-02-06",
      "close": 451.5657
    },
    {
      "date": "2024-02-07",
      "close": 466.3325
    },
    {
      "date": "2024-02-08",
      "close": 466.7396
    },
    {
      "date": "2024-02-09",
      "close": 464.8628
    },
    {
      "date": "2024-02-12",
      "close": 465.6473
    },
    {
      "date": "2024-02-13",
      "close": 456.9282
    },
    {
      "date": "2024-02-14",
      "close": 469.9969
    },
    {
      "date": "2024-02-15",
      "close": 480.6724
    },
    {
      "date": "2024-02-16",
      "close": 470.0367
    },
    {
      "date": "2024-02-20",
      "close": 468.4775
    },
    {
      "date": "2024-02-21",
      "close": 465.2765
    },
    {
      "date": "2024-02-22",
      "close": 483.27
    },
    {
      "date": "2024-02-23",
      "close": 481.1823
    },
    {
      "date": "2024-02-26",
      "close": 478.9058
    },
    {
      "date": "2024-02-27",
      "close": 484.1846
    },
    {
      "date": "2024-02-28",
      "close": 481.1724
    },
    {
      "date": "2024-02-29",
      "close": 487.2465
    },
    {
      "date": "2024-03-01",
      "close": 499.3448
    },
    {
      "date": "2024-03-04",
      "close": 495.2591
    },
    {
      "date": "2024-03-05",
      "close": 487.3359
    },
    {
      "date": "2024-03-06",
      "close": 493.1714
    },
    {
      "date": "2024-03-07",
      "close": 509.1767
    },
    {
      "date": "2024-03-08",
      "close": 502.9734
    },
    {
      "date": "2024-03-11",
      "close": 480.7449
    },
    {
      "date": "2024-03-12",
      "close": 496.8099
    },
    {
      "date": "2024-03-13",
      "close": 492.6545
    },
    {
      "date": "2024-03-14",
      "close": 488.9365
    },
    {
      "date": "2024-03-15",
      "close": 481.252
    },
    {
      "date": "2024-03-18",
      "close": 494.0562
    },
    {
      "date": "2024-03-19",
      "close": 493.3205
    },
    {
      "date": "2024-03-20",
      "close": 502.5459
    },
    {
      "date": "2024-03-21",
      "close": 504.7728
    },
    {
      "date": "2024-03-22",
      "close": 506.582
    },
    {
      "date": "2024-03-25",
      "close": 500.0606
    },
    {
      "date": "2024-03-26",
      "close": 492.9726
    },
    {
      "date": "2024-03-27",
      "close": 490.9545
    },
    {
      "date": "2024-03-28",
      "close": 482.7232
    }
  ]
}