{
  "schema_version": "asset_state_v2",
  "ticker": "JNJ",
  "year": 2022,
  "quarter": "Q4",
  "as_of": "2022-12-31",
  "features": {
    "close": 160.4,
    "ret_20d": -0.0117,
    "ret_60d": 0.0768,
    "ret_120d": 0.0178,
    "ret_252d": 0.0521,
    "vol_20d": 0.1167,
    "vol_60d": 0.1499,
    "vol_120d": 0.1582,
    "downside_vol_60d": 0.1139,
    "drawdown_60d": -0.0321,
    "max_drawdown_1y": -0.1274,
    "sma_20d": 160.96,
    "sma_50d": 158.44,
    "sma_200d": 155.84,
    "momentum_200d": 1.0292,
    "momentum_12_1": 0.0602,
    "idiosyncratic_momentum": 0.0675,
    "trend_consistency": 0.6167,
    "sharpe_60d": 2.0726,
    "beta_1y": 0.3044,
    "size_log_mcap": null,
    "value_book_to_market": null,
    "avg_dollar_volume_20d": 993844401.19,
    "gross_margin": null,
    "roe": null,
    "free_cash_flow_yield": null,
    "debt_to_equity": null,
    "earnings_surprise_pct": 0.0241
  }
}