{
  "schema_version": "asset_state_v2",
  "ticker": "JPM",
  "year": 2023,
  "quarter": "Q1",
  "as_of": "2023-03-31",
  "features": {
    "close": 119.92,
    "ret_20d": -0.0873,
    "ret_60d": -0.0401,
    "ret_120d": 0.1994,
    "ret_252d": -0.058,
    "vol_20d": 0.4043,
    "vol_60d": 0.2753,
    "vol_120d": 0.2721,
    "downside_vol_60d": 0.2299,
    "drawdown_60d": -0.1314,
    "max_drawdown_1y": -0.2594,
    "sma_20d": 122.45,
    "sma_50d": 127.5,
    "sma_200d": 115.75,
    "momentum_200d": 1.0361,
    "momentum_12_1": 0.043,
    "idiosyncratic_momentum": -0.1003,
    "trend_consistency": 0.55,
    "sharpe_60d": -0.6244,
    "beta_1y": 0.8717,
    "size_log_mcap": null,
    "value_book_to_market": null,
    "avg_dollar_volume_20d": 2596276892.65,
    "gross_margin": null,
    "roe": null,
    "free_cash_flow_yield": null,
    "debt_to_equity": null,
    "earnings_surprise_pct": 0.1516
  }
}