{
  "case_data": {
    "items": [
      {
        "kind": "news",
        "content": "RFK Jr. and His Allies Target Trump\u2019s Beloved Soda RFK Jr. and His Allies Target Trump\u2019s Beloved Soda",
        "impact_score": 3.36420893407134e-109
      },
      {
        "kind": "news",
        "content": "Why The S&P 500 Is A Hold Ahead Of February Jobs Report The upcoming February non-farm payrolls report is expected to show another increase in jobs, with government employment likely to weaken. Read my analysis here.",
        "impact_score": -5.710878966432017e-110
      },
      {
        "kind": "news",
        "content": "VDC Consumer Staples ETF: Good Diversifier, Buy On Weakness VDC is a defensive ETF with low correlation to the US stock market. Read why this consumer staples ETF could be a prudent choice for long-term investors.",
        "impact_score": -1.0392510304431618e-109
      },
      {
        "kind": "news",
        "content": "Coca Cola : Global Insider Trading Compliance Policy The Coca-Cola Company Global Insider Trading Compliance Policy Introduction The Coca-Cola Company has adopted this...",
        "impact_score": 0.0
      },
      {
        "kind": "news",
        "content": "Warren Buffett Stocks: What's Inside Berkshire Hathaway's Portfolio? Warren Buffett Stocks: What's Inside Berkshire Hathaway's Portfolio?",
        "impact_score": 0.0
      },
      {
        "kind": "news",
        "content": "Coca-Cola Co. stock underperforms Monday when compared to competitors despite daily gains Coca-Cola Co. stock underperforms Monday when compared to competitors despite daily gains",
        "impact_score": -2.6541185559369507e-109
      },
      {
        "kind": "news",
        "content": "A Quiet March Will Bring Annual Increases From Seven More Dividend Growth Companies ",
        "impact_score": 2.4675022094806883e-109
      },
      {
        "kind": "news",
        "content": "Tech Sector Hammered As Trump's Tariff Plans Spark Market Selloff: Nvidia, ARM, Super Micro Lead Tech Bloodbath U.S. markets suffered a steep selloff Monday as President Donald Trump announced sweeping new tariffs, extending last week&#39;s losses and driving declines across all major sectors.",
        "impact_score": -1.8515546511798092e-110
      },
      {
        "kind": "news",
        "content": "Dogs Of The Dow Chase A \"Safer\" Buy For March My monthly update and commentary on the top dividend stock picks from the Dogs Of The Dow, March 2025 edition. Click here to read more about Dogs of the Dow.",
        "impact_score": 2.077406721745356e-109
      },
      {
        "kind": "news",
        "content": "Coca-Cola Co. stock underperforms Tuesday when compared to competitors Coca-Cola Co. stock underperforms Tuesday when compared to competitors",
        "impact_score": 0.0
      },
      {
        "kind": "news",
        "content": "2 Attractively Priced, High Yield Stocks For Income Durability As The Market Hits New Highs Hyperinflation and high interest rates make dividend-paying stocks attractive. Read why PFE and BTI stocks could be great portfolio additions.",
        "impact_score": 1.5582864307200377e-108
      },
      {
        "kind": "news",
        "content": "The Dividend Aristocrats Ranked By Quality Scores: March 2025 S&P Dow Jones Indices added three new members to the S&P 500 Dividend Aristocrats Index. Click here to find out my ranking of dividend aristocrats.",
        "impact_score": 0.0
      },
      {
        "kind": "news",
        "content": "Trump\u2019s tariffs worry companies. Here\u2019s what they\u2019re saying about the uncertainty. Trump\u2019s tariffs worry companies. Here\u2019s what they\u2019re saying about the uncertainty.",
        "impact_score": -1.981439338932347e-108
      },
      {
        "kind": "news",
        "content": "Whitbread: The Story Of Beer, Pubs, And Hotels Whitbread has shifted focus from restaurants to hotel operations, especially Premier Inn, and is expanding in London and Germany due to falling UK F&B sales.",
        "impact_score": -1.1740746287951103e-108
      },
      {
        "kind": "news",
        "content": "Consumer Staples Are Crushing the Market. Why They Aren\u2019t the Stocks to Buy. Consumer Staples Are Crushing the Market. Why They Aren\u2019t the Stocks to Buy.",
        "impact_score": -5.169564190847506e-108
      },
      {
        "kind": "news",
        "content": "Dividend Champion, Contender, And Challenger Highlights: Week Of March 9 Read here for weekly updates on Dividend Champions, Contenders, and Challengers. Track dividend changes, ex-dividend dates, and upcoming pay dates.",
        "impact_score": 9.53993379695965e-108
      },
      {
        "kind": "news",
        "content": "A Major Market Rotation Is Likely Coming The market hasn\u00e2\u0080\u0099t priced in several undervalued AI stocks. Read why these stocks could outperform tech in the next market cycle.",
        "impact_score": 0.0
      },
      {
        "kind": "news",
        "content": "54 Upcoming Dividend Increases, Including A King My strategy focuses on companies with consistent dividend growth and outperforming benchmarks. Check out this week's dividend increases.",
        "impact_score": 8.046479240467326e-108
      },
      {
        "kind": "news",
        "content": "What Investors Should Expect From February's Consumer Price Index Report February CPI report is crucial after January saw a 0.5% increase, with 3.0% inflation over the past year. Check out what investors should expect from the report.",
        "impact_score": 9.079226049922041e-108
      },
      {
        "kind": "news",
        "content": "Where I Would Invest As Market Fear Picks Up Despite recent S&P 500 sluggishness, I see opportunities in ETFs and REITs offering good value. Check out the recommended ETF and REIT picks.",
        "impact_score": 3.632454549298458e-107
      },
      {
        "kind": "news",
        "content": "Zacks Investment Ideas feature highlights: Coca-Cola, Philip Morris and Johnson & Johnson Coca-Cola, Philip Morris and Johnson & Johnson are part of the Zacks Investment Ideas article.",
        "impact_score": 0.0
      },
      {
        "kind": "news",
        "content": "2 Warren Buffett Dividend Stocks to Buy Hand Over Fist in March Warren Buffett's investing skills have created enormous wealth for his investors.  From 1965 through 2024, he delivered a 5,502,284% cumulative return for Berkshire Hathaway shareholders.  If you're interested in building passive income, Berkshire's stock portfolio is full of outstanding businesses that pay regular dividends.",
        "impact_score": 6.648841360458138e-107
      },
      {
        "kind": "news",
        "content": "3 ETFs To Help You Navigate Market Volatility, Recession Risks Bond market is warning of economic slowdown, causing investors to shift towards defensive assets like ETFs that focus on stability and essential industries.",
        "impact_score": -5.554823995464726e-108
      },
      {
        "kind": "news",
        "content": "Stock market sell-off: Why these stocks are in the green amid the pain The shift to defense is on.",
        "impact_score": -3.145271568594083e-107
      },
      {
        "kind": "news",
        "content": "Mutual Funds Flock To This Warren Buffett Favorite Mutual funds are adding more defensive stocks as the market continues to trend downward. One name is a long-term Warren Buffett holding.",
        "impact_score": 3.9868240455164454e-107
      },
      {
        "kind": "news",
        "content": "The Coca-Cola Company (KO): Among the Top Stocks to Buy According to Citadel Investment Group We recently published an article titled Top 12 Stocks to Buy According to Citadel Investment Group. In this article, we are going to take a look at where The Coca-Cola Company (NYSE:KO) stands against the other stocks. Citadel Investment Group was officially founded by Ken Griffin on November 1, 1990, with $4.2 million in assets under [\u2026]",
        "impact_score": 3.894543767104042e-107
      },
      {
        "kind": "news",
        "content": "Invesco Global Core Equity Fund Q4 2024 Commentary Global equity returns were mixed in the fourth quarter, with developed equities outperforming emerging market equities.",
        "impact_score": 0.0
      },
      {
        "kind": "news",
        "content": "3 Crucial Things Investors Should Do During the Nasdaq Correction The tech-heavy Nasdaq Composite stock index has been one of the big winners of the artificial intelligence (AI) boom.  The benchmark roared higher over the past two years, posting consecutive double-digit gains, as investors piled into players present in this hot growth area.  President Donald Trump recently launched tariffs on imports from China, Canada, and Mexico -- a move to protest the flow of lethal drugs and illegal immigrants across borders and into the U.S., the Trump administration says.",
        "impact_score": 9.300894191508909e-107
      },
      {
        "kind": "news",
        "content": "Is The Coca-Cola Company (KO) the Best Low Risk Stock to Buy In 2025? We recently compiled a list of the 10 Best Low Risk Stocks To Buy in 2025. In this article, we are going to take a look at where The Coca-Cola Company (NYSE:KO) stands against the other low risk stocks. Risk is a key consideration in investing and portfolio management, as investors generally aim to achieve the [\u2026]",
        "impact_score": -4.2893370910534065e-107
      },
      {
        "kind": "news",
        "content": "Coca-Cola Stock Trades Above 50 & 200-Day SMAs: Entry Point or Wait? KO's strong market position and strategies fuel long-term growth, but inflation, macro risks and valuation concerns pose challenges amid economic uncertainty.",
        "impact_score": -4.5832176604183473e-107
      },
      {
        "kind": "news",
        "content": "Coca-Cola (KO) Stock Moves -0.57%: What You Should Know In the latest trading session, Coca-Cola (KO) closed at $71.04, marking a -0.57% move from the previous day.",
        "impact_score": 0.0
      },
      {
        "kind": "news",
        "content": "Fidelity Select Consumer Staples Portfolio Q4 2024 Review For the quarter, the fund's Retail Class shares returned -6.25%, lagging the -2.64% result of the MSCI U.S. IMI Consumer Staples 25/50 Index. Read more here.",
        "impact_score": 4.282210139597196e-108
      },
      {
        "kind": "news",
        "content": "2 No-Brainer Warren Buffett Stocks to Buy Right Now Warren Buffett has made some of his greatest investments when stock prices are down, and his company continues to hold several quality stocks that can help you build wealth for retirement.  Berkshire Hathaway holds shares of several top companies that have passed inspection of one of the greatest investors of all time.  Coca-Cola (NYSE: KO) and American Express (NYSE: AXP) are two of Buffett's favorite businesses of all time, considering how long Berkshire has held their shares.",
        "impact_score": 2.1278876273757244e-106
      },
      {
        "kind": "news",
        "content": "Coca-Cola Consolidated: An Under-The-Radar Bottler With Great Pricing Power Learn why Coca-Cola Consolidated, Inc.'s strong pricing power and diverse brand portfolio signal a 24% upside potential to its fair value. Click for more on COKE.",
        "impact_score": 2.4556865693436514e-106
      },
      {
        "kind": "news",
        "content": "Steel & Aluminum Import Tariff Threat: 4 ETFs Gaining & Losing In The Market Shake-Up Trump announced a 50% tariff on Canadian aluminum and steel imports, it created a cloud of fear and uncertainty in the markets.",
        "impact_score": -2.2078038627298443e-106
      },
      {
        "kind": "news",
        "content": "35.2% of Warren Buffett's $281 Billion Portfolio Is Invested in 3 Artificial Intelligence (AI) Stocks Warren Buffett is the CEO of the Berkshire Hathaway (NYSE: BRK.A)(NYSE: BRK.B) holding company, where he oversees a $281 billion portfolio of publicly traded stocks and securities, in addition to several privately held subsidiaries.  Berkshire is also sitting on a record $334 billion in cash, which Buffett and his team can deploy when they spot new opportunities.  Had you invested $1,000 in Berkshire stock when Buffett took the helm in 1965, it would be worth an eye-popping $44.7 million today.",
        "impact_score": 3.7167418305274984e-106
      },
      {
        "kind": "news",
        "content": "3 No-Brainer Warren Buffett Stocks to Buy Right Now The Oracle of Omaha, as Warren Buffett is known, has an incredible track record as an investor, and he frequently offers words of wisdom to his many fans.  If you're looking for some investments to shore up your own portfolio as the volatility on Wall Street intensifies, Amazon (NASDAQ: AMZN), American Express (NYSE: AXP), and Coca-Cola (NYSE: KO) are three great and resilient stocks that have also earned Buffett's stamp of approval.",
        "impact_score": 4.3200073895844354e-106
      },
      {
        "kind": "news",
        "content": "CocaCola Company (The) (KO) Is a Trending Stock: Facts to Know Before Betting on It Zacks.com users have recently been watching Coca-Cola (KO) quite a bit. Thus, it is worth knowing the facts that could determine the stock's prospects.",
        "impact_score": 2.431222229891372e-106
      },
      {
        "kind": "earnings",
        "content": "Coca-Cola (KO) Up 1.8% Since Last Earnings Report: Can It Continue? Coca-Cola (KO) reported earnings 30 days ago. What's next for the stock? We take a look at earnings estimates for some clues.",
        "impact_score": 0.0
      },
      {
        "kind": "news",
        "content": "5 Soft Drinks Stocks Showing Resilience Amid Cost & Tariff Woes Beverages - Soft Drinks industry presents growth opportunities, driven by innovation and digital transformation. Yet, it grapples with cost inflation, tariff uncertainties and supply-chain challenges. Top players such as KO, PEP, MNST, KDP and PRMB stand out as strong investment options.",
        "impact_score": 4.364736217487803e-106
      },
      {
        "kind": "news",
        "content": "If You Could Only Buy 1 Dividend Stock, This Would Be It Defensive stocks remain popular, but valuations are stretched. Learn to balance stability and opportunity in a volatile market. Click for more.",
        "impact_score": 5.954993305510246e-106
      },
      {
        "kind": "news",
        "content": "'WPP Loses Coca-Cola Media Work In North America' - Financial Times https://www.ft.com/content/5ee92217-712e-47a6-81c9-059e56757dd9",
        "impact_score": -3.3115517494256423e-106
      },
      {
        "kind": "news",
        "content": "WPP Loses Coca-Cola Media Work In North America- FT March 14 - * WPP LOSES COCA-COLA MEDIA WORK IN NORTH AMERICA- FT * PUBLICIS WINS COKE MANDATE IN US AND CANADA FROMLONDON-LISTEDRIVAL - FTSource text:...",
        "impact_score": 2.6853866892087185e-107
      },
      {
        "kind": "news",
        "content": "\"Publicis Wins Coke Mandate In U.S. And Canada From London-Listed Rival\" - Financial Times https://www.ft.com/content/5ee92217-712e-47a6-81c9-059e56757dd9",
        "impact_score": 5.956524466693569e-106
      },
      {
        "kind": "news",
        "content": "Zacks Industry Outlook Highlights Coca-Cola, PepsiCo, Monster Beverage, Keurig Dr Pepper and Primo Brands Coca-Cola, PepsiCo, Monster Beverage, Keurig Dr Pepper and Primo Brands are part of the Zacks Industry Outlook article.",
        "impact_score": 0.0
      },
      {
        "kind": "news",
        "content": "Market Chatter: WPP Loses Coca-Cola's North American Media Work to Publicis WPP (WPP) lost Coca-Cola's (KO) media buying and planning account in the US and Canada to French riv",
        "impact_score": -6.938426103325158e-106
      },
      {
        "kind": "news",
        "content": "Update: Market Chatter: WPP Loses Coca-Cola's North American Media Work to Publicis (Updates with Coca-Cola's response in the fourth and fifth paragraphs.) WPP (WPP) lost Coca-Cola'",
        "impact_score": -7.184184489555336e-106
      },
      {
        "kind": "news",
        "content": "Best Stock to Buy Right Now: PepsiCo vs. Coca-Cola PepsiCo (NASDAQ: PEP) has been one of those relative winners so far in 2025, with shares up slightly even as the S&P 500 dropped 5%.  Let's take a closer look at that beverage and snack food giant to see how it stacks up against its main drink rival, Coca-Cola (NYSE: KO).  Coca-Cola is the clear growth winner, despite consumers becoming more price-sensitive in the past year.",
        "impact_score": 1.2683670381760123e-105
      },
      {
        "kind": "news",
        "content": "What Stock Market Sell-Off? These 2 Dow Jones Dividend Stocks Are Near Their All-Time Highs Stock market volatility is back, with the S&P 500, Nasdaq Composite, and Dow Jones Industrial Average all down year to date -- with their declines led by sell-offs in growth-focused sectors like technology and consumer discretionary.  Dow components\u00a0Procter & Gamble (NYSE: PG) and Coca-Cola (NYSE: KO) are hovering around their all-time highs.",
        "impact_score": 6.510948372499612e-106
      },
      {
        "kind": "news",
        "content": "Inside Coca-Cola\u2019s packaging overhaul Coca-Cola is advancing its \u201cWorld Without Waste\u201d strategy, targeting 100% recyclable packaging by 2025 and 50% recycled material by 2030.",
        "impact_score": 0.0
      },
      {
        "kind": "news",
        "content": "Coca-Cola CEO James Quincey's 2024 Salary $28 Mln - Filing Coca-Cola Co: * COCA-COLA CEO JAMES QUINCEY'S 2024 SALARY $28 MILLION - FILINGSource text:Further company coverage: ...",
        "impact_score": 0.0
      },
      {
        "kind": "news",
        "content": "Coca-Cola cracks open Minute Maid vodka cocktails The beverage giant's alcohol subsidiary is leaning into the rapid growth of spirits-infused canned drinks.",
        "impact_score": 2.9862190953565435e-105
      },
      {
        "kind": "news",
        "content": "Publicis\u2019 Coke media account win could be landing at just the right time Activity in the prebiotic soda space is primed to ramp up as Coke promotes its first offering in the category and PepsiCo acquires Poppi.",
        "impact_score": 5.788404258859773e-105
      },
      {
        "kind": "news",
        "content": "Kandhari seeks Indian regulatory approval for HCCB assets buy The deal involves assets in northern Gujarat and the Union Territory of Diu.",
        "impact_score": 5.588514506480118e-105
      },
      {
        "kind": "news",
        "content": "Is Coca-Cola Consolidated, Inc. (COKE) the Best Low Float Stock to Invest in Now? We recently published a list of 8 Best Low Float Stocks to Invest in Now. In this article, we are going to take a look at where Coca-Cola Consolidated, Inc. (NASDAQ:COKE) stands against other best low float stocks to invest in now. Stocks with low public float refer to shares of a company that are [\u2026]",
        "impact_score": 7.159178304287544e-105
      },
      {
        "kind": "news",
        "content": "PepsiCo strikes near-$2bn deal to buy Poppi The US drinks giant said it was looking to meet consumers\u2019 \u201cgrowing interest in health and wellness\u201d.",
        "impact_score": 1.0741948050823295e-105
      },
      {
        "kind": "news",
        "content": "Should You Invest in Coca-Cola (KO) Based on Bullish Wall Street Views? The average brokerage recommendation (ABR) for Coca-Cola (KO) is equivalent to a Buy. The overly optimistic recommendations of Wall Street analysts make the effectiveness of this highly sought-after metric questionable. So, is it worth buying the stock?",
        "impact_score": 2.7934871953530413e-105
      },
      {
        "kind": "news",
        "content": "How much Trump's liquor tariffs could cost 2 giant liquor producers The bottom lines of two big liquor giants could be hammered.",
        "impact_score": 0.0
      },
      {
        "kind": "news",
        "content": "Pepsi to Buy Poppi for Nearly $2 Billion, Broadening Brand Portfolio PepsiCo  said it is buying the prebiotic soda brand Poppi for nearly $2 billion, sending shares of the food and beverage company 1.6% higher.  The news comes as Pepsi and its rivals have been seeking to expand their product portfolios to drive further growth as economic conditions and changing tastes among consumers weigh on demand.  Inflation has squeezed consumers\u2019 budgets, hurting demand for sodas and snacks.",
        "impact_score": 3.0429746630915427e-105
      },
      {
        "kind": "earnings",
        "content": "Coca-Cola (KO) Beats Stock Market Upswing: What Investors Need to Know Coca-Cola (KO) concluded the recent trading session at $70.12, signifying a +1.39% move from its prior day's close.",
        "impact_score": 0.0
      },
      {
        "kind": "news",
        "content": "These 6 Warren Buffett Stocks Are Soaring in 2025 While the Market Is Sinking \"A rising tide lifts all boats,\" according to an often-cited adage.  Warren Buffett seems to have a knack for finding stocks that perform well when the overall market is performing dismally.  This performance would probably bring a smile to Buffett's long-term business partner, Charlie Munger, who died in late 2023.",
        "impact_score": 0.0
      },
      {
        "kind": "news",
        "content": "Coca-Cola Co. stock outperforms competitors despite losses on the day Coca-Cola Co. stock outperforms competitors despite losses on the day",
        "impact_score": 9.78626093149858e-105
      },
      {
        "kind": "news",
        "content": "Coca-Cola (NYSE:KO) Faces Surge In Shareholder Proposals Ahead Of April Meeting Coca-Cola (NYSE:KO) has experienced a notable 10.60% price increase over the past quarter, amid a backdrop of shareholder activism and market volatility. Recent proposals from shareholders addressed topics like executive pay and corporate governance, but these were largely recommended against by the company. This shareholder-centric climate coincided with the announcement of Coca-Cola's increased dividend and ongoing share buyback initiatives, potentially signaling confidence to the market...",
        "impact_score": 1.710511600321062e-104
      },
      {
        "kind": "news",
        "content": "Coca-Cola\u2019s CEO didn\u2019t drink a Coke at his first staff meeting\u2014here\u2019s why James Quincey shared his perspective on leadership and innovation during Adobe's annual event.",
        "impact_score": 1.9146128543254315e-104
      },
      {
        "kind": "news",
        "content": "The Coca-Cola Company pulls Minute Maid brand into spirits The new offerings are part of the Minute Maid Spiked line, which first launched with a \"flavoured wine cocktails\" range in late 2023.",
        "impact_score": 4.226247290313486e-105
      },
      {
        "kind": "news",
        "content": "Coca-Cola (KO) Stock Sinks As Market Gains: What You Should Know Coca-Cola (KO) closed the most recent trading day at $69.28, moving -0.14% from the previous trading session.",
        "impact_score": 1.4443351092824053e-104
      },
      {
        "kind": "news",
        "content": "My Dividend Stock Portfolio: New February Dividend Record - 100 Holdings With 11 Buys February investments fell below $1,000, mainly in BDCs like Owl Rock Capital and Ares Capital, boosting annual dividend income by $77.",
        "impact_score": 3.593275583185584e-104
      },
      {
        "kind": "news",
        "content": "Buy 4 Ideal 'Safer' February Dividends, Out Of 40 Choices From Readers Discover top dividend-paying stocks with potential gains! Explore investment insights, high-yield underdogs, and safe picks for optimal portfolio growth.",
        "impact_score": 5.841576196920817e-104
      },
      {
        "kind": "news",
        "content": "Defensive Stocks For Unpredictable Trump Policy Navigate market volatility with defensive stocks, bonds, and gold.",
        "impact_score": 3.2454587856070844e-105
      },
      {
        "kind": "news",
        "content": "The Coca-Cola Company (KO): Among Defensive Dividend Stocks to Buy During Market Sell Off We recently published a list of 10 Defensive Dividend Stocks To Buy During Market Sell Off. In this article, we are going to take a look at where The Coca-Cola Company (NYSE:KO) stands against other defensive dividend stocks to buy during market sell off. The importance of defensive dividend stocks only becomes clear when the [\u2026]",
        "impact_score": 5.0680389982882175e-104
      },
      {
        "kind": "news",
        "content": "Historic Dividend Outperformance For year to date performance, the biggest losers are now mostly growth factors, whereas low volatility and dividend focused ETFs are actually still in the green so far in 2025.",
        "impact_score": -6.1187683343377215e-105
      },
      {
        "kind": "news",
        "content": "Nike, NVIDIA Corp. share losses contribute to Dow's 233-point drop Nike, NVIDIA Corp. share losses contribute to Dow's 233-point drop",
        "impact_score": -7.762603757000446e-104
      },
      {
        "kind": "news",
        "content": "Coke Florida Announces Key Leadership Changes; Andy Hill to Lead Customer and Commercial Operations, Thomas Benford Becomes Advisor to CEO TAMPA, Fla -Coca-Cola Beverages Florida, LLC announced that Andy Hill, Chief Customer Officer, will immediately take on the expanded role of Chief Customer and Commercial Officer, reporting to Troy...",
        "impact_score": 0.0
      },
      {
        "kind": "news",
        "content": "Nike, Coca-Cola share losses contribute to Dow's nearly 125-point fall Nike, Coca-Cola share losses contribute to Dow's nearly 125-point fall",
        "impact_score": -3.1651262317483554e-104
      },
      {
        "kind": "news",
        "content": "2025 Dividend Kings: Strong Run Continues Discover the top-performing Dividend Kings of 2025, outperforming the S&P 500 by 4.57%. Click here to explore more promising picks.",
        "impact_score": 9.591713086836936e-104
      },
      {
        "kind": "earnings",
        "content": "3 Reasons to Buy Coca-Cola Stock Like There's No Tomorrow It's not every day, or every year, that Coca-Cola (NYSE: KO) stock beats the market.  Coca-Cola stock is up 12% this year, while the S&P 500 is down 4%.  It's as good a time as ever to understand why Coca-Cola is such a great stock to own.",
        "impact_score": 1.081430166432859e-103
      },
      {
        "kind": "news",
        "content": "1 Buffett Berkshire Near-Buy In 15 'Safer' Dividend 38 Dogs My monthly update and commentary on top dividend stock picks from Berkshire Hathaway's holdings and Buffett's portfolio, March 2025 edition. Click to read more.",
        "impact_score": 2.953752524038771e-104
      },
      {
        "kind": "news",
        "content": "Should You Forget Sirius XM? This Stock Has Made Far More Millionaires Don't be so enamored by a scintillating story that you forget to consider the fundamentals like marketability and profitability, and the likelihood of both in the future.",
        "impact_score": 9.379600877536803e-104
      },
      {
        "kind": "news",
        "content": "SCHD: Good Times Aren't Great (Rating Downgrade) Learn why SCHD underperforms the S&P 500 and how its focus on dividend growth impacts valuation.",
        "impact_score": 1.4359936645275404e-103
      },
      {
        "kind": "news",
        "content": "Philip Morris International Is On Fire With Zyn: More Gains Ahead? Philip Morris surged 66% in the past year, outperforming even Nvidia amidst a market shift towards quality investments. Read why PM stock is a Buy.",
        "impact_score": 5.097530967005787e-104
      },
      {
        "kind": "news",
        "content": "Is Coca-Cola the Best Warren Buffett Stock to Buy Right Now? If I were Warren Buffett, I probably wouldn't be able to wipe the smile off my face.  While the overall stock market has fallen this year, his beloved Berkshire Hathaway has delivered an impressive gain of around 17%.  The Coca-Cola Company (NYSE: KO) is in that group, jumping nearly 10% year to date.",
        "impact_score": 8.962063396358344e-103
      },
      {
        "kind": "earnings",
        "content": "Warren Buffett's $24B Coca-Cola Bet Still Pays Off\u2014Stock Nears Record High As 'Big Money Managers Scoop Up Shares' In a market environment that's anything but calm, both individual investors and mutual fund managers are rethinking their strategies. Growth stocks are proving elusive, so many are turning to defensive names\u2014a tactic long embraced by Warren Buffett. Investor's Business Daily's \"Stocks That Funds Are Buying\" screener recently highlighted 14 stocks that fit the bill. Among these, Coca\u2011Cola (NYSE:KO) and O'Reilly Automotive (NYSE:ORLY) are getting a lot of attention. Don't Miss: Deloitte's fastest-",
        "impact_score": 1.0647303464641798e-102
      },
      {
        "kind": "news",
        "content": "FPA Queens Road Value Fund Q4 2024 Commentary FPA Queens Road Value Fund (\u00e2\u0080\u009cFund\u00e2\u0080\u009d) returned -2.69% for the fourth quarter of 2024. Click here to read the full commentary. ",
        "impact_score": 1.0799958280674823e-102
      },
      {
        "kind": "news",
        "content": "The Smartest Dividend Stocks to Buy With $350 Right Now Recession-resilient businesses with generous dividends could benefit investors in a volatile market environment.",
        "impact_score": 1.6393914461879995e-102
      },
      {
        "kind": "earnings",
        "content": "These Were the 2 Top-Performing Stocks in the Dow Jones Industrial Average in February 2025 The Dow Jones Industrial Average (DJINDICES: ^DJI) index dropped 1.6% in February.  Although some blue chip stocks slumped by double-digit percentages, 50% of its 30 constituents beat the index last month.  Coca-Cola (NYSE: KO) and Verizon Communications (NYSE: VZ) were the two top-performing Dow stocks in February, gaining 12.2% and 9.4%, respectively.",
        "impact_score": 1.2612991229684575e-102
      },
      {
        "kind": "news",
        "content": "Is The Coca-Cola Company's (NYSE:KO) ROE Of 40% Impressive? While some investors are already well versed in financial metrics (hat tip), this article is for those who would like...",
        "impact_score": 1.3816078462877296e-102
      },
      {
        "kind": "news",
        "content": "Is Coca-Cola Company (KO) The Best Defensive Stock Amid Market Volatility? We recently published a list of 15 Best Defensive Stocks Amid Market Volatility In this article, we are going to take a look at where Coca-Cola Company (NYSE:KO) stands against other best defensive stocks amid market volatility. With ongoing inflation, economic uncertainty, and global tensions, more investors are looking for ways to protect their money [\u2026]",
        "impact_score": 2.500542636762491e-102
      },
      {
        "kind": "news",
        "content": "Coca-Cola (KO) Stock Falls Amid Market Uptick: What Investors Need to Know Coca-Cola (KO) reachead $68.81 at the closing of the latest trading day, reflecting a -0.2% change compared to its last close.",
        "impact_score": 0.0
      },
      {
        "kind": "news",
        "content": "Coca-Cola Company (KO) Finds A Place Among the Top 10 Stocks In Balyasny\u2019s Portfolio We recently published a list of Top 10 Stocks to Buy According to Balyasny Asset Management. In this article, we are going to take a look at where The Coca-Cola Company (NYSE:KO) stands against other top stocks to buy according to Balyasny Asset Management. Balyasny Asset Management (BAM) is a leading investment management firm headquartered in [\u2026]",
        "impact_score": 2.782162436250308e-102
      },
      {
        "kind": "news",
        "content": "These Dividend Stocks Can Protect You From the Next Market Drop These Dividend Stocks Can Protect You From the Next Market Drop",
        "impact_score": 9.160988327876e-103
      },
      {
        "kind": "news",
        "content": "Coca-Cola Recalls 10,000 Cans Over Possible Plastic Contamination Coca-Cola Recalls 10,000 Cans Over Possible Plastic Contamination",
        "impact_score": 0.0
      },
      {
        "kind": "earnings",
        "content": "Coca-Cola Targeted in EU Antitrust Probe, Bloomberg Says, Citing Sources Coca-Cola's European business was targeted by a European Commission antitrust raid earlier this month, Bloomberg says, citing unnamed sources. --The people didn't specify whether the officials...",
        "impact_score": 0.0
      },
      {
        "kind": "news",
        "content": "Coke refreshes \u2018Share a Coke\u2019 to reach Gen Z with digital experiences The brand is bringing back an iconic effort with a focus on shareability and customization to engage a cohort of digital natives that crave authenticity.",
        "impact_score": 1.6684087898469992e-102
      },
      {
        "kind": "news",
        "content": "Market Chatter: Coca-Cola Facilities in Europe Targeted in EU Antitrust Raids Coca-Cola's (KO) Europe business was one of the unidentified targets of European Union antitrust rai",
        "impact_score": 0.0
      },
      {
        "kind": "earnings",
        "content": "Coca Cola bottlers raided by EU antitrust regulators, source says Coca Cola bottlers were raided by EU antitrust regulators earlier this month, a person with direct knowledge of the matter said.  The European Commission announced the raids on non-alcoholic drinks companies in several EU countries on March 10 but did not name them.  The raids targeted Coca Cola bottlers, the person said, declining to provide details because of the sensitivity of the matter.",
        "impact_score": 2.4765960065781886e-103
      },
      {
        "kind": "earnings",
        "content": "Coca-Cola (NYSE:KO) Faces Shareholder Push On Political Spending Alignment The latest shareholder activism involving As You Sow, who urged Coca-Cola (NYSE:KO) shareholders to vote for a proposal to report on political spending, emphasized the increasing demand for corporate accountability. This followed a quarter where the company increased its dividend by 5.2% and repurchased shares worth $559 million. Meanwhile, Coca-Cola's earnings report highlighted a slight decline in net income despite a 2.9% market rise over the last week. Amid a general market backdrop...",
        "impact_score": 2.76929093501618e-102
      },
      {
        "kind": "news",
        "content": "FDA warns of possible plastic in recalled Coca-Cola cans The voluntary recall includes 864 12-packs, totaling over 10,000 cans.",
        "impact_score": -4.994515982780755e-103
      },
      {
        "kind": "news",
        "content": "Strategically Building A $100,000 Dividend Portfolio For Attractive Income And Strong Risk-Adjusted Returns The Dividend Income Accelerator Portfolio focuses on financially healthy companies with strong balance sheets. Check out the recent additions to the portfolio.",
        "impact_score": 4.4612743899958885e-102
      },
      {
        "kind": "news",
        "content": "Coca-Cola (KO) Gains As Market Dips: What You Should Know The latest trading day saw Coca-Cola (KO) settling at $70.02, representing a +1.76% change from its previous close.",
        "impact_score": 1.856269118131378e-102
      },
      {
        "kind": "news",
        "content": "What's Going On With Coca-Cola Stock Today? Coca-Cola shares are slightly higher amid a Class II recall of contaminated beverages, but the company continues to focus on sustainability efforts.",
        "impact_score": 1.211958939323853e-102
      },
      {
        "kind": "news",
        "content": "Coca-Cola to invest over $1.4 bln in Argentina Coca-ColaArgentina and bottlers will invest more than $1.4 billion in theSouth American country to boost production, improve logistics,and optimize infrastructure, the company said in a statement...",
        "impact_score": 7.150415919639792e-102
      },
      {
        "kind": "news",
        "content": "Coca-Cola\u2019s plastic usage to reportedly exceed 9.1 billion pounds by 2030 The company recently discarded its goal to increase reusable packaging to 25% of its sales by 2030.",
        "impact_score": -2.2424856806337997e-103
      },
      {
        "kind": "news",
        "content": "Is Coca-Cola Company (KO) the Best Roth IRA Stock to Buy According to Analysts? We recently published a list of 10 Best Roth IRA Stocks to Buy According to Analysts. In this article, we are going to take a look at where The Coca-Cola Company (NYSE:KO) stands against other best Roth IRA stocks to buy according to analysts. A Roth IRA, or individual retirement account, is a tax-advantaged savings [\u2026]",
        "impact_score": 8.1747470996371e-102
      },
      {
        "kind": "earnings",
        "content": "Coca-Cola business in Europe target of EU antitrust raid, Bloomberg reports Coca-Cola\u2019s (KO) European business was among unidentified targets of EU antitrust raids that occurred earlier in March, Bloomberg\u2019s Samuel Stolton reports, citing people familiar with the probe. On March 10, the European Commission said it was carrying out inspections at the premises of businesses active in the non-alcoholic beverages space in several member states, though declined to mention the names of the companies examined, the author notes. Published first on TheFly \u2013 the ultimate source f",
        "impact_score": 3.673180084139802e-102
      },
      {
        "kind": "news",
        "content": "Coca-Cola Co. stock outperforms competitors on strong trading day Coca-Cola Co. stock outperforms competitors on strong trading day",
        "impact_score": 7.183929556599898e-102
      },
      {
        "kind": "news",
        "content": "Coca-Cola to invest over $1.4 billion in Argentina Coca-Cola Argentina and bottlers will invest more than $1.4 billion in the South American country to boost production, improve logistics, and optimize infrastructure, the company said in a statement on Thursday.",
        "impact_score": 8.075351194149585e-102
      },
      {
        "kind": "news",
        "content": "Why The Coca-Cola Company (KO) Is Among the Best Coffee Stocks to Buy Now We recently published a list of the 11 Best Coffee Stocks to Buy Now. In this article, we are going to take a look at where The Coca-Cola Company (NYSE:KO) stands against the other best coffee stocks to buy now. Overview of the Coffee Sector According to the US National Coffee Association, the number of [\u2026]",
        "impact_score": 9.492275269220536e-102
      },
      {
        "kind": "earnings",
        "content": "The Coca-Cola Company Announces Timing of First Quarter 2025 Earnings Release ATLANTA, March 27, 2025--The Coca-Cola Company today announced it will release first quarter 2025 financial results April 29 before the New York Stock Exchange opens. The release will be followed by an investor conference call at 8:30 a.m. ET to discuss the results.",
        "impact_score": 0.0
      },
      {
        "kind": "news",
        "content": "Putnam Large Cap Value Fund Q4 2024 Commentary While US stocks overall posted a gain in the fourth quarter, value stocks fared differently, posting a modest negative return for the period.",
        "impact_score": 6.17643515247007e-102
      },
      {
        "kind": "news",
        "content": "Arca Continental Coca-Cola Southwest Beverages Wins 2025 Market Street Challenge DALLAS - Arca Continental Coca-Cola Southwest Beverages , the Coca-Cola bottler for Texas and parts of Oklahoma, New Mexico and Arkansas, has been named the winner of the Coca-Cola Market Street...",
        "impact_score": 1.1651739810125438e-101
      },
      {
        "kind": "news",
        "content": "Coca-Cola\u2019s plastic will surpass 9 billion pounds by end of decade: report The beverage giant, which recently pared back some packaging goals, is facing criticism from green groups concerned about its environmental commitments.",
        "impact_score": -5.236069499034891e-102
      },
      {
        "kind": "news",
        "content": "Coca Cola : Fourth Quarter 2024 Investor Overview \u2013 Updated as of December 31, 2024 Investor Relations Overview Updated as of December 31, 2024 KEY THEMES FOR TODAY ...",
        "impact_score": 0.0
      },
      {
        "kind": "news",
        "content": "3 Consumer Stocks Walking a Fine Line Consumer staples stocks are solid insurance policies in frothy markets ripe for corrections. Unfortunately, the sector hasn\u2019t provided much protection lately as it pulled back by 10% over the past six months. This drop was worse than the S&P 500\u2019s 1.6% fall.",
        "impact_score": -1.0648863379184892e-101
      },
      {
        "kind": "earnings",
        "content": "Lamb Weston Q3 Earnings on Deck: Key Factors You Should Understand LW's fiscal third-quarter results are likely to reflect the adverse impact of sluggish restaurant traffic and overcapacity in the global market.",
        "impact_score": -1.0702392035686365e-101
      },
      {
        "kind": "news",
        "content": "Watching PepsiCo, Coca-Cola, Monster Beverage, Keurig Dr Pepper; Shares Move Lower 'RFK Jr. Pushes Ban On Soda From Being Purchased With Food Stamps' - Washington Post https://www.washingtonpost.com/health/2025/03/28/soda-ban-food-stamps-rfk-west-virginia/\n",
        "impact_score": -9.626412712405674e-102
      },
      {
        "kind": "news",
        "content": "2 Surefire Dividend Stocks That Could Pay You for Life Dividend investing is an excellent strategy for (at least) two reasons.  Here are two companies that can pull it off: Amgen (NASDAQ: AMGN) and Coca-Cola (NYSE: KO).  Amgen paid its first dividend in 2011.",
        "impact_score": 1.1229168021408765e-101
      },
      {
        "kind": "news",
        "content": "Shares of beverage and soft drink companies are trading lower after HHS Secretary RFK Jr. said he would seek to bar soda purchases using food stamps. ",
        "impact_score": 0.0
      },
      {
        "kind": "news",
        "content": "Soda stocks drop as food stamp band push gains momentum Soda stocks, including Pepsi (PEP), Coca-Cola (KO), and Keurig Dr Pepper (KDP), are falling on Friday after Robert Kennedy Jr. reportedly announced his plan to seek federal help in banning the use of food stamps for soda purchases, according to the Washington Post. Market Domination hosts Josh Lipton and Julie Hyman discuss the implications of this proposal and how it could impact the beverage industry. To watch more expert insights and analysis on the latest market action, check out more Morning Brief\u00a0here.",
        "impact_score": 6.049041677551033e-102
      },
      {
        "kind": "news",
        "content": "Dividend Champion, Contender, And Challenger Highlights: Week Of March 30 Stay updated on dividend trends with a weekly summary of Dividend Champions, Contenders, and Challengers.",
        "impact_score": 2.148784397841008e-101
      },
      {
        "kind": "news",
        "content": "2 Top Dividend Stocks to Buy and Hold Forever With enough time and persistence, anyone can build a stock portfolio that pays thousands of dollars in dividend income every year.  Dividend investing may not be the most efficient way to build wealth in the stock market, but there's no other style of investing that can compete with the warm feeling of having cash automatically deposited into your account every year from some of the strongest companies in the world.  Here are two timeless consumer brands that could pay you for the rest of your life.",
        "impact_score": 2.3378579677367157e-101
      },
      {
        "kind": "news",
        "content": "This High-Yield Warren Buffett Stock Has Increased Its Dividend for 63 Consecutive Years. Is It a No-Brainer Buy Right Now? In January 1967, Berkshire Hathaway did something it's done only once in the company's history: It paid a cash dividend.  Aside from that one time, Buffett has prioritized using Berkshire's profits to reinvest in growth, rather than rewarding shareholders with dividends.",
        "impact_score": 2.7207008398234404e-101
      },
      {
        "kind": "news",
        "content": "$14K Investor In TSLA, NVDA, And QQQ Faces Dilemma \u2013 'Looking To Hold For At Least 10 Years' But Is That A Recipe For Disaster? Reddit Debates Knowing which stocks to hold for the long term and which to sell before they drag down your portfolio is a challenge every investor faces at least once in their journey.",
        "impact_score": -2.6204784260834675e-101
      },
      {
        "kind": "news",
        "content": "The 2 Smartest Dividend Stocks to Buy Right Now Dividend stocks are a blessing to investors because they provide income and don't rely on stock price appreciation to reward shareholders.  You can't go wrong with dividend payouts at any time, but they're especially helpful when there's a lot of uncertainty in the stock market.  If you want investment income without worrying too much about stock price movements, the following two dividend stocks are worth adding to your stock portfolio.",
        "impact_score": 5.154174666090856e-101
      },
      {
        "kind": "news",
        "content": "Buy 3 'Safer' Dividend Kings Of 25 From March's 55 ",
        "impact_score": 0.0
      },
      {
        "kind": "news",
        "content": "Is Coca-Cola Company (KO) the Best Consumer Staples Stock to Buy According to Analysts? We recently published a list of 10 Best Consumer Staples Stocks to Buy According to Analysts. In this article, we are going to take a look at where The Coca-Cola Company (NYSE:KO) stands against other best consumer staples stocks to buy according to analysts. Is the US Economy Headed for a Recession? Consumer confidence is [\u2026]",
        "impact_score": 6.401801866781112e-101
      },
      {
        "kind": "earnings",
        "content": "'Banks Will Never Go Out Of Business'\u2014Jim Cramer Says JPMorgan Is Too Cheap To Ignore As It Hits Record $58.5B Profit Jim Cramer, host of CNBC's \"Mad Money,\" has recently highlighted a range of stocks that some believe will withstand market volatility and provide steady long-term returns. His recommendations often spark both interest and discussion among investors. Market Movements and Mixed Signals Coca-Cola (NYSE:KO) remains among Cramer's top choices. The beverage giant posted a 6% increase in fourth-quarter revenue, reaching $11.5 billion, while adjusted earnings per share rose 12% to $0.51. Don't Miss: Are",
        "impact_score": 5.718672264641447e-101
      },
      {
        "kind": "news",
        "content": "The Coca-Cola Company: First Quarter Results Belies Valuation Concerns Coca-Cola's recent modest sales volume increase was misleading, and its growth valuation looks overly optimistic. Read why KO stock is a Sell.",
        "impact_score": 5.014726075783747e-101
      }
    ]
  },
  "stock_data": {
    "KO": {
      "ticker": "KO",
      "current_price": 71.62000274658203,
      "daily_bars": [
        {
          "timestamp": "2025-01-02",
          "close": 61.84000015258789
        },
        {
          "timestamp": "2025-01-03",
          "close": 61.75
        },
        {
          "timestamp": "2025-01-06",
          "close": 60.810001373291016
        },
        {
          "timestamp": "2025-01-07",
          "close": 60.84000015258789
        },
        {
          "timestamp": "2025-01-08",
          "close": 61.709999084472656
        },
        {
          "timestamp": "2025-01-10",
          "close": 61.06999969482422
        },
        {
          "timestamp": "2025-01-13",
          "close": 61.650001525878906
        },
        {
          "timestamp": "2025-01-14",
          "close": 62.040000915527344
        },
        {
          "timestamp": "2025-01-15",
          "close": 61.77000045776367
        },
        {
          "timestamp": "2025-01-16",
          "close": 62.25
        },
        {
          "timestamp": "2025-01-17",
          "close": 62.709999084472656
        },
        {
          "timestamp": "2025-01-21",
          "close": 62.41999816894531
        },
        {
          "timestamp": "2025-01-22",
          "close": 61.779998779296875
        },
        {
          "timestamp": "2025-01-23",
          "close": 61.529998779296875
        },
        {
          "timestamp": "2025-01-24",
          "close": 61.91999816894531
        },
        {
          "timestamp": "2025-01-27",
          "close": 63.869998931884766
        },
        {
          "timestamp": "2025-01-28",
          "close": 62.36000061035156
        },
        {
          "timestamp": "2025-01-29",
          "close": 62.83000183105469
        },
        {
          "timestamp": "2025-01-30",
          "close": 64.05000305175781
        },
        {
          "timestamp": "2025-01-31",
          "close": 63.47999954223633
        },
        {
          "timestamp": "2025-02-03",
          "close": 63.349998474121094
        },
        {
          "timestamp": "2025-02-04",
          "close": 62.66999816894531
        },
        {
          "timestamp": "2025-02-05",
          "close": 63.119998931884766
        },
        {
          "timestamp": "2025-02-06",
          "close": 63.36000061035156
        },
        {
          "timestamp": "2025-02-07",
          "close": 63.84000015258789
        },
        {
          "timestamp": "2025-02-10",
          "close": 64.55000305175781
        },
        {
          "timestamp": "2025-02-11",
          "close": 67.5999984741211
        },
        {
          "timestamp": "2025-02-12",
          "close": 68.70999908447266
        },
        {
          "timestamp": "2025-02-13",
          "close": 69.5
        },
        {
          "timestamp": "2025-02-14",
          "close": 68.87000274658203
        },
        {
          "timestamp": "2025-02-18",
          "close": 69.05000305175781
        },
        {
          "timestamp": "2025-02-19",
          "close": 70.06999969482422
        },
        {
          "timestamp": "2025-02-20",
          "close": 70.04000091552734
        },
        {
          "timestamp": "2025-02-21",
          "close": 71.3499984741211
        },
        {
          "timestamp": "2025-02-24",
          "close": 70.58999633789062
        },
        {
          "timestamp": "2025-02-25",
          "close": 71.48999786376953
        },
        {
          "timestamp": "2025-02-26",
          "close": 70.80000305175781
        },
        {
          "timestamp": "2025-02-27",
          "close": 70.87000274658203
        },
        {
          "timestamp": "2025-02-28",
          "close": 71.20999908447266
        },
        {
          "timestamp": "2025-03-03",
          "close": 72.31999969482422
        },
        {
          "timestamp": "2025-03-04",
          "close": 70.19000244140625
        },
        {
          "timestamp": "2025-03-05",
          "close": 70.08000183105469
        },
        {
          "timestamp": "2025-03-06",
          "close": 70.45999908447266
        },
        {
          "timestamp": "2025-03-07",
          "close": 71.43000030517578
        },
        {
          "timestamp": "2025-03-10",
          "close": 71.44999694824219
        },
        {
          "timestamp": "2025-03-11",
          "close": 71.04000091552734
        },
        {
          "timestamp": "2025-03-12",
          "close": 69.94000244140625
        },
        {
          "timestamp": "2025-03-13",
          "close": 69.62000274658203
        },
        {
          "timestamp": "2025-03-14",
          "close": 69.16000366210938
        },
        {
          "timestamp": "2025-03-17",
          "close": 70.12000274658203
        },
        {
          "timestamp": "2025-03-18",
          "close": 69.37999725341797
        },
        {
          "timestamp": "2025-03-19",
          "close": 69.27999877929688
        },
        {
          "timestamp": "2025-03-20",
          "close": 69.70999908447266
        },
        {
          "timestamp": "2025-03-21",
          "close": 68.66999816894531
        },
        {
          "timestamp": "2025-03-24",
          "close": 68.94999694824219
        },
        {
          "timestamp": "2025-03-25",
          "close": 68.80999755859375
        },
        {
          "timestamp": "2025-03-26",
          "close": 70.0199966430664
        },
        {
          "timestamp": "2025-03-27",
          "close": 70.73999786376953
        },
        {
          "timestamp": "2025-03-28",
          "close": 70.37000274658203
        },
        {
          "timestamp": "2025-03-31",
          "close": 71.62000274658203
        }
      ]
    }
  }
}