{
  "schema_version": "daily_prices_v1",
  "ticker": "JPM",
  "year": 2023,
  "quarter": "Q2",
  "start_date": "2023-04-03",
  "end_date": "2023-06-30",
  "trading_days": 62,
  "daily_close": [
    {
      "date": "2023-04-03",
      "close": 121.2317
    },
    {
      "date": "2023-04-04",
      "close": 119.6111
    },
    {
      "date": "2023-04-05",
      "close": 119.7894
    },
    {
      "date": "2023-04-06",
      "close": 119.658
    },
    {
      "date": "2023-04-10",
      "close": 120.0523
    },
    {
      "date": "2023-04-11",
      "close": 120.6437
    },
    {
      "date": "2023-04-12",
      "close": 120.6249
    },
    {
      "date": "2023-04-13",
      "close": 121.0849
    },
    {
      "date": "2023-04-14",
      "close": 130.228
    },
    {
      "date": "2023-04-17",
      "close": 131.2606
    },
    {
      "date": "2023-04-18",
      "close": 132.7343
    },
    {
      "date": "2023-04-19",
      "close": 132.5654
    },
    {
      "date": "2023-04-20",
      "close": 132.1805
    },
    {
      "date": "2023-04-21",
      "close": 131.927
    },
    {
      "date": "2023-04-24",
      "close": 132.1054
    },
    {
      "date": "2023-04-25",
      "close": 129.2329
    },
    {
      "date": "2023-04-26",
      "close": 126.9424
    },
    {
      "date": "2023-04-27",
      "close": 128.6509
    },
    {
      "date": "2023-04-28",
      "close": 129.768
    },
    {
      "date": "2023-05-01",
      "close": 132.5466
    },
    {
      "date": "2023-05-02",
      "close": 130.4063
    },
    {
      "date": "2023-05-03",
      "close": 127.6465
    },
    {
      "date": "2023-05-04",
      "close": 125.9005
    },
    {
      "date": "2023-05-05",
      "close": 128.3599
    },
    {
      "date": "2023-05-08",
      "close": 128.6697
    },
    {
      "date": "2023-05-09",
      "close": 128.0501
    },
    {
      "date": "2023-05-10",
      "close": 128.1158
    },
    {
      "date": "2023-05-11",
      "close": 127.7122
    },
    {
      "date": "2023-05-12",
      "close": 125.8817
    },
    {
      "date": "2023-05-15",
      "close": 126.9424
    },
    {
      "date": "2023-05-16",
      "close": 126.0882
    },
    {
      "date": "2023-05-17",
      "close": 129.9651
    },
    {
      "date": "2023-05-18",
      "close": 130.9507
    },
    {
      "date": "2023-05-19",
      "close": 130.6504
    },
    {
      "date": "2023-05-22",
      "close": 129.5709
    },
    {
      "date": "2023-05-23",
      "close": 128.2191
    },
    {
      "date": "2023-05-24",
      "close": 127.0457
    },
    {
      "date": "2023-05-25",
      "close": 127.3555
    },
    {
      "date": "2023-05-26",
      "close": 128.5477
    },
    {
      "date": "2023-05-30",
      "close": 129.0358
    },
    {
      "date": "2023-05-31",
      "close": 127.3931
    },
    {
      "date": "2023-06-01",
      "close": 129.1484
    },
    {
      "date": "2023-06-02",
      "close": 131.8613
    },
    {
      "date": "2023-06-05",
      "close": 130.5659
    },
    {
      "date": "2023-06-06",
      "close": 130.8006
    },
    {
      "date": "2023-06-07",
      "close": 132.0678
    },
    {
      "date": "2023-06-08",
      "close": 132.1054
    },
    {
      "date": "2023-06-09",
      "close": 132.3682
    },
    {
      "date": "2023-06-12",
      "close": 132.3588
    },
    {
      "date": "2023-06-13",
      "close": 133.3163
    },
    {
      "date": "2023-06-14",
      "close": 132.8188
    },
    {
      "date": "2023-06-15",
      "close": 134.3207
    },
    {
      "date": "2023-06-16",
      "close": 134.4803
    },
    {
      "date": "2023-06-20",
      "close": 133.7951
    },
    {
      "date": "2023-06-21",
      "close": 133.598
    },
    {
      "date": "2023-06-22",
      "close": 131.0258
    },
    {
      "date": "2023-06-23",
      "close": 130.3406
    },
    {
      "date": "2023-06-26",
      "close": 130.6598
    },
    {
      "date": "2023-06-27",
      "close": 130.6691
    },
    {
      "date": "2023-06-28",
      "close": 130.0965
    },
    {
      "date": "2023-06-29",
      "close": 134.6399
    },
    {
      "date": "2023-06-30",
      "close": 136.5268
    }
  ]
}