{
  "schema_version": "asset_state_v2",
  "ticker": "CAT",
  "year": 2024,
  "quarter": "Q4",
  "as_of": "2024-12-31",
  "features": {
    "close": 356.77,
    "ret_20d": -0.1061,
    "ret_60d": -0.0685,
    "ret_120d": 0.1136,
    "ret_252d": 0.2424,
    "vol_20d": 0.1832,
    "vol_60d": 0.2739,
    "vol_120d": 0.2872,
    "downside_vol_60d": 0.1478,
    "drawdown_60d": -0.1356,
    "max_drawdown_1y": -0.1583,
    "sma_20d": 373.57,
    "sma_50d": 379.97,
    "sma_200d": 352.03,
    "momentum_200d": 1.0135,
    "momentum_12_1": 0.3816,
    "idiosyncratic_momentum": -0.1154,
    "trend_consistency": 0.4333,
    "sharpe_60d": -1.0876,
    "beta_1y": 1.2207,
    "size_log_mcap": 25.8621,
    "value_book_to_market": 0.1143,
    "avg_dollar_volume_20d": 688223095.53,
    "gross_margin": 0.3426,
    "roe": 0.1432,
    "free_cash_flow_yield": 0.0138,
    "debt_to_equity": 1.9706,
    "earnings_surprise_pct": -0.0336
  }
}