{
  "schema_version": "daily_prices_v1",
  "ticker": "NVDA",
  "year": 2023,
  "quarter": "Q1",
  "start_date": "2023-01-03",
  "end_date": "2023-03-31",
  "trading_days": 62,
  "daily_close": [
    {
      "date": "2023-01-03",
      "close": 14.3007
    },
    {
      "date": "2023-01-04",
      "close": 14.7343
    },
    {
      "date": "2023-01-05",
      "close": 14.2507
    },
    {
      "date": "2023-01-06",
      "close": 14.8441
    },
    {
      "date": "2023-01-09",
      "close": 15.6124
    },
    {
      "date": "2023-01-10",
      "close": 15.8931
    },
    {
      "date": "2023-01-11",
      "close": 15.985
    },
    {
      "date": "2023-01-12",
      "close": 16.4945
    },
    {
      "date": "2023-01-13",
      "close": 16.8821
    },
    {
      "date": "2023-01-17",
      "close": 17.6843
    },
    {
      "date": "2023-01-18",
      "close": 17.3596
    },
    {
      "date": "2023-01-19",
      "close": 16.7482
    },
    {
      "date": "2023-01-20",
      "close": 17.8212
    },
    {
      "date": "2023-01-23",
      "close": 19.1738
    },
    {
      "date": "2023-01-24",
      "close": 19.2457
    },
    {
      "date": "2023-01-25",
      "close": 19.3037
    },
    {
      "date": "2023-01-26",
      "close": 19.7822
    },
    {
      "date": "2023-01-27",
      "close": 20.3446
    },
    {
      "date": "2023-01-30",
      "close": 19.1428
    },
    {
      "date": "2023-01-31",
      "close": 19.5175
    },
    {
      "date": "2023-02-01",
      "close": 20.9221
    },
    {
      "date": "2023-02-02",
      "close": 21.6873
    },
    {
      "date": "2023-02-03",
      "close": 21.0789
    },
    {
      "date": "2023-02-06",
      "close": 21.0679
    },
    {
      "date": "2023-02-07",
      "close": 22.1508
    },
    {
      "date": "2023-02-08",
      "close": 22.1828
    },
    {
      "date": "2023-02-09",
      "close": 22.3147
    },
    {
      "date": "2023-02-10",
      "close": 21.2437
    },
    {
      "date": "2023-02-13",
      "close": 21.7662
    },
    {
      "date": "2023-02-14",
      "close": 22.948
    },
    {
      "date": "2023-02-15",
      "close": 22.7412
    },
    {
      "date": "2023-02-16",
      "close": 21.98
    },
    {
      "date": "2023-02-17",
      "close": 21.3666
    },
    {
      "date": "2023-02-21",
      "close": 20.6343
    },
    {
      "date": "2023-02-22",
      "close": 20.7332
    },
    {
      "date": "2023-02-23",
      "close": 23.6403
    },
    {
      "date": "2023-02-24",
      "close": 23.2627
    },
    {
      "date": "2023-02-27",
      "close": 23.4775
    },
    {
      "date": "2023-02-28",
      "close": 23.1928
    },
    {
      "date": "2023-03-01",
      "close": 22.6753
    },
    {
      "date": "2023-03-02",
      "close": 23.2907
    },
    {
      "date": "2023-03-03",
      "close": 23.8661
    },
    {
      "date": "2023-03-06",
      "close": 23.5304
    },
    {
      "date": "2023-03-07",
      "close": 23.2687
    },
    {
      "date": "2023-03-08",
      "close": 24.1609
    },
    {
      "date": "2023-03-09",
      "close": 23.4165
    },
    {
      "date": "2023-03-10",
      "close": 22.9459
    },
    {
      "date": "2023-03-13",
      "close": 22.9469
    },
    {
      "date": "2023-03-14",
      "close": 24.043
    },
    {
      "date": "2023-03-15",
      "close": 24.2079
    },
    {
      "date": "2023-03-16",
      "close": 25.5198
    },
    {
      "date": "2023-03-17",
      "close": 25.7036
    },
    {
      "date": "2023-03-20",
      "close": 25.8785
    },
    {
      "date": "2023-03-21",
      "close": 26.1772
    },
    {
      "date": "2023-03-22",
      "close": 26.446
    },
    {
      "date": "2023-03-23",
      "close": 27.1684
    },
    {
      "date": "2023-03-24",
      "close": 26.7568
    },
    {
      "date": "2023-03-27",
      "close": 26.509
    },
    {
      "date": "2023-03-28",
      "close": 26.3881
    },
    {
      "date": "2023-03-29",
      "close": 26.9616
    },
    {
      "date": "2023-03-30",
      "close": 27.3603
    },
    {
      "date": "2023-03-31",
      "close": 27.7539
    }
  ]
}