{
  "schema_version": "asset_state_v2",
  "ticker": "GS",
  "year": 2021,
  "quarter": "Q3",
  "as_of": "2021-09-30",
  "features": {
    "close": 344.15,
    "ret_20d": -0.0692,
    "ret_60d": 0.0457,
    "ret_120d": 0.1731,
    "ret_252d": 0.9905,
    "vol_20d": 0.2372,
    "vol_60d": 0.2443,
    "vol_120d": 0.2406,
    "downside_vol_60d": 0.1364,
    "drawdown_60d": -0.1001,
    "max_drawdown_1y": -0.1192,
    "sma_20d": 355.97,
    "sma_50d": 353.27,
    "sma_200d": 308.25,
    "momentum_200d": 1.1165,
    "momentum_12_1": 1.1287,
    "idiosyncratic_momentum": 0.034,
    "trend_consistency": 0.45,
    "sharpe_60d": 0.7682,
    "beta_1y": 0.9879,
    "size_log_mcap": null,
    "value_book_to_market": null,
    "avg_dollar_volume_20d": 856151541.22,
    "gross_margin": null,
    "roe": null,
    "free_cash_flow_yield": null,
    "debt_to_equity": null,
    "earnings_surprise_pct": 0.4754
  }
}