{
  "schema_version": "asset_state_v2",
  "ticker": "UNH",
  "year": 2024,
  "quarter": "Q4",
  "as_of": "2024-12-31",
  "features": {
    "close": 493.7,
    "ret_20d": -0.1655,
    "ret_60d": -0.1411,
    "ret_120d": 0.0104,
    "ret_252d": -0.0241,
    "vol_20d": 0.4283,
    "vol_60d": 0.3686,
    "vol_120d": 0.3061,
    "downside_vol_60d": 0.3273,
    "drawdown_60d": -0.2205,
    "max_drawdown_1y": -0.2205,
    "sma_20d": 514.9,
    "sma_50d": 548.63,
    "sma_200d": 522.74,
    "momentum_200d": 0.9444,
    "momentum_12_1": 0.1727,
    "idiosyncratic_momentum": -0.1665,
    "trend_consistency": 0.5,
    "sharpe_60d": -1.7328,
    "beta_1y": 0.1221,
    "size_log_mcap": 26.8364,
    "value_book_to_market": 0.2051,
    "avg_dollar_volume_20d": 3582022093.06,
    "gross_margin": 0.2114,
    "roe": 0.0598,
    "free_cash_flow_yield": 0.0032,
    "debt_to_equity": 0.83,
    "earnings_surprise_pct": 0.0171
  }
}