{
  "schema_version": "asset_state_v2",
  "ticker": "NFLX",
  "year": 2024,
  "quarter": "Q2",
  "as_of": "2024-06-30",
  "features": {
    "close": 67.49,
    "ret_20d": 0.042,
    "ret_60d": 0.0711,
    "ret_120d": 0.4236,
    "ret_252d": 0.5701,
    "vol_20d": 0.2105,
    "vol_60d": 0.3219,
    "vol_120d": 0.3163,
    "downside_vol_60d": 0.2893,
    "drawdown_60d": -0.1345,
    "max_drawdown_1y": -0.2751,
    "sma_20d": 66.09,
    "sma_50d": 62.56,
    "sma_200d": 53.14,
    "momentum_200d": 1.2699,
    "momentum_12_1": 0.5229,
    "idiosyncratic_momentum": -0.0129,
    "trend_consistency": 0.5333,
    "sharpe_60d": 0.8963,
    "beta_1y": 1.3157,
    "size_log_mcap": null,
    "value_book_to_market": null,
    "avg_dollar_volume_20d": 1932138647.2,
    "gross_margin": null,
    "roe": null,
    "free_cash_flow_yield": null,
    "debt_to_equity": null,
    "earnings_surprise_pct": 0.1778
  }
}