{
  "schema_version": "daily_prices_v1",
  "ticker": "CVX",
  "year": 2023,
  "quarter": "Q4",
  "start_date": "2023-10-02",
  "end_date": "2023-12-29",
  "trading_days": 63,
  "daily_close": [
    {
      "date": "2023-10-02",
      "close": 149.5423
    },
    {
      "date": "2023-10-03",
      "close": 149.8925
    },
    {
      "date": "2023-10-04",
      "close": 146.3995
    },
    {
      "date": "2023-10-05",
      "close": 147.1718
    },
    {
      "date": "2023-10-06",
      "close": 145.6722
    },
    {
      "date": "2023-10-09",
      "close": 149.7039
    },
    {
      "date": "2023-10-10",
      "close": 149.5423
    },
    {
      "date": "2023-10-11",
      "close": 144.6575
    },
    {
      "date": "2023-10-12",
      "close": 144.7743
    },
    {
      "date": "2023-10-13",
      "close": 147.3154
    },
    {
      "date": "2023-10-16",
      "close": 148.5186
    },
    {
      "date": "2023-10-17",
      "close": 150.4851
    },
    {
      "date": "2023-10-18",
      "close": 151.6794
    },
    {
      "date": "2023-10-19",
      "close": 151.841
    },
    {
      "date": "2023-10-20",
      "close": 149.8027
    },
    {
      "date": "2023-10-23",
      "close": 144.2804
    },
    {
      "date": "2023-10-24",
      "close": 140.6617
    },
    {
      "date": "2023-10-25",
      "close": 139.9613
    },
    {
      "date": "2023-10-26",
      "close": 138.9556
    },
    {
      "date": "2023-10-27",
      "close": 129.6171
    },
    {
      "date": "2023-10-30",
      "close": 131.1795
    },
    {
      "date": "2023-10-31",
      "close": 130.8563
    },
    {
      "date": "2023-11-01",
      "close": 129.2849
    },
    {
      "date": "2023-11-02",
      "close": 133.577
    },
    {
      "date": "2023-11-03",
      "close": 132.5444
    },
    {
      "date": "2023-11-06",
      "close": 131.9966
    },
    {
      "date": "2023-11-07",
      "close": 129.671
    },
    {
      "date": "2023-11-08",
      "close": 127.8661
    },
    {
      "date": "2023-11-09",
      "close": 127.4531
    },
    {
      "date": "2023-11-10",
      "close": 128.36
    },
    {
      "date": "2023-11-13",
      "close": 129.3028
    },
    {
      "date": "2023-11-14",
      "close": 130.2457
    },
    {
      "date": "2023-11-15",
      "close": 130.7036
    },
    {
      "date": "2023-11-16",
      "close": 128.6349
    },
    {
      "date": "2023-11-17",
      "close": 131.0756
    },
    {
      "date": "2023-11-20",
      "close": 131.003
    },
    {
      "date": "2023-11-21",
      "close": 130.6945
    },
    {
      "date": "2023-11-22",
      "close": 130.9577
    },
    {
      "date": "2023-11-24",
      "close": 131.4748
    },
    {
      "date": "2023-11-27",
      "close": 130.9849
    },
    {
      "date": "2023-11-28",
      "close": 132.0283
    },
    {
      "date": "2023-11-29",
      "close": 130.5766
    },
    {
      "date": "2023-11-30",
      "close": 130.2953
    },
    {
      "date": "2023-12-01",
      "close": 131.3932
    },
    {
      "date": "2023-12-04",
      "close": 131.4476
    },
    {
      "date": "2023-12-05",
      "close": 129.6239
    },
    {
      "date": "2023-12-06",
      "close": 129.3244
    },
    {
      "date": "2023-12-07",
      "close": 129.2246
    },
    {
      "date": "2023-12-08",
      "close": 130.9395
    },
    {
      "date": "2023-12-11",
      "close": 130.9758
    },
    {
      "date": "2023-12-12",
      "close": 129.2972
    },
    {
      "date": "2023-12-13",
      "close": 131.2117
    },
    {
      "date": "2023-12-14",
      "close": 136.0388
    },
    {
      "date": "2023-12-15",
      "close": 135.5126
    },
    {
      "date": "2023-12-18",
      "close": 135.812
    },
    {
      "date": "2023-12-19",
      "close": 137.5904
    },
    {
      "date": "2023-12-20",
      "close": 136.3292
    },
    {
      "date": "2023-12-21",
      "close": 136.7466
    },
    {
      "date": "2023-12-22",
      "close": 137.055
    },
    {
      "date": "2023-12-26",
      "close": 138.289
    },
    {
      "date": "2023-12-27",
      "close": 137.8354
    },
    {
      "date": "2023-12-28",
      "close": 135.8937
    },
    {
      "date": "2023-12-29",
      "close": 135.3402
    }
  ]
}