{
  "schema_version": "daily_prices_v1",
  "ticker": "CVX",
  "year": 2024,
  "quarter": "Q4",
  "start_date": "2024-10-01",
  "end_date": "2024-12-31",
  "trading_days": 64,
  "daily_close": [
    {
      "date": "2024-10-01",
      "close": 140.2512
    },
    {
      "date": "2024-10-02",
      "close": 141.4222
    },
    {
      "date": "2024-10-03",
      "close": 141.7033
    },
    {
      "date": "2024-10-04",
      "close": 141.2255
    },
    {
      "date": "2024-10-07",
      "close": 141.5815
    },
    {
      "date": "2024-10-08",
      "close": 139.3611
    },
    {
      "date": "2024-10-09",
      "close": 140.2043
    },
    {
      "date": "2024-10-10",
      "close": 141.1131
    },
    {
      "date": "2024-10-11",
      "close": 141.8626
    },
    {
      "date": "2024-10-14",
      "close": 142.1999
    },
    {
      "date": "2024-10-15",
      "close": 138.4055
    },
    {
      "date": "2024-10-16",
      "close": 139.3424
    },
    {
      "date": "2024-10-17",
      "close": 141.6565
    },
    {
      "date": "2024-10-18",
      "close": 141.2349
    },
    {
      "date": "2024-10-21",
      "close": 141.3567
    },
    {
      "date": "2024-10-22",
      "close": 141.3942
    },
    {
      "date": "2024-10-23",
      "close": 140.9819
    },
    {
      "date": "2024-10-24",
      "close": 140.9538
    },
    {
      "date": "2024-10-25",
      "close": 141.2911
    },
    {
      "date": "2024-10-28",
      "close": 141.0381
    },
    {
      "date": "2024-10-29",
      "close": 139.1456
    },
    {
      "date": "2024-10-30",
      "close": 138.7053
    },
    {
      "date": "2024-10-31",
      "close": 139.4267
    },
    {
      "date": "2024-11-01",
      "close": 143.4084
    },
    {
      "date": "2024-11-04",
      "close": 144.2516
    },
    {
      "date": "2024-11-05",
      "close": 143.727
    },
    {
      "date": "2024-11-06",
      "close": 147.765
    },
    {
      "date": "2024-11-07",
      "close": 146.8749
    },
    {
      "date": "2024-11-08",
      "close": 147.0248
    },
    {
      "date": "2024-11-11",
      "close": 146.622
    },
    {
      "date": "2024-11-12",
      "close": 145.4883
    },
    {
      "date": "2024-11-13",
      "close": 148.7018
    },
    {
      "date": "2024-11-14",
      "close": 151.5874
    },
    {
      "date": "2024-11-15",
      "close": 151.2314
    },
    {
      "date": "2024-11-18",
      "close": 152.1495
    },
    {
      "date": "2024-11-19",
      "close": 151.0516
    },
    {
      "date": "2024-11-20",
      "close": 152.6889
    },
    {
      "date": "2024-11-21",
      "close": 152.9729
    },
    {
      "date": "2024-11-22",
      "close": 153.6638
    },
    {
      "date": "2024-11-25",
      "close": 151.7709
    },
    {
      "date": "2024-11-26",
      "close": 153.8247
    },
    {
      "date": "2024-11-27",
      "close": 153.4272
    },
    {
      "date": "2024-11-29",
      "close": 153.2568
    },
    {
      "date": "2024-12-02",
      "close": 153.5218
    },
    {
      "date": "2024-12-03",
      "close": 153.2473
    },
    {
      "date": "2024-12-04",
      "close": 149.8401
    },
    {
      "date": "2024-12-05",
      "close": 150.7961
    },
    {
      "date": "2024-12-06",
      "close": 146.9251
    },
    {
      "date": "2024-12-09",
      "close": 148.6666
    },
    {
      "date": "2024-12-10",
      "close": 148.5908
    },
    {
      "date": "2024-12-11",
      "close": 147.8432
    },
    {
      "date": "2024-12-12",
      "close": 146.4235
    },
    {
      "date": "2024-12-13",
      "close": 145.6285
    },
    {
      "date": "2024-12-16",
      "close": 141.36
    },
    {
      "date": "2024-12-17",
      "close": 140.177
    },
    {
      "date": "2024-12-18",
      "close": 136.3629
    },
    {
      "date": "2024-12-19",
      "close": 133.5898
    },
    {
      "date": "2024-12-20",
      "close": 135.1987
    },
    {
      "date": "2024-12-23",
      "close": 135.3123
    },
    {
      "date": "2024-12-24",
      "close": 136.1357
    },
    {
      "date": "2024-12-26",
      "close": 136.2682
    },
    {
      "date": "2024-12-27",
      "close": 136.2871
    },
    {
      "date": "2024-12-30",
      "close": 135.407
    },
    {
      "date": "2024-12-31",
      "close": 137.0822
    }
  ]
}