{
  "metadata": {
    "ticker": "AAPL",
    "year": "2025",
    "quarter": "Q2",
    "original_char_length": 84619,
    "compressed_char_length": 2395
  },
  "company_overview": {
    "headline_result": "beat",
    "management_tone": "stable",
    "primary_theme": "Strong revenue growth despite tariff pressures"
  },
  "financials": {
    "revenue": {
      "actual": "95.4 billion",
      "consensus": "not disclosed",
      "delta_vs_consensus": "not disclosed",
      "yoy_growth": "5%"
    },
    "eps": {
      "actual": "1.65",
      "consensus": "not disclosed",
      "delta_vs_consensus": "not disclosed",
      "yoy_growth": "8%"
    },
    "gross_margin": "47.1%",
    "operating_margin": "not disclosed",
    "free_cash_flow": "24 billion"
  },
  "guidance": {
    "next_quarter": "low to mid-single digits revenue growth",
    "full_year": "not disclosed",
    "guidance_change_vs_prior": "unchanged",
    "reason_for_change": "not disclosed"
  },
  "segment_highlights": [
    {
      "segment": "iPhone",
      "performance": "46.8 billion, up 2%",
      "driver": "iPhone 16 family"
    },
    {
      "segment": "Mac",
      "performance": "7.9 billion, up 7%",
      "driver": "M4-powered MacBook Air"
    },
    {
      "segment": "iPad",
      "performance": "6.4 billion, up 15%",
      "driver": "M3-powered iPad Air"
    },
    {
      "segment": "Wearables, Home and Accessories",
      "performance": "7.5 billion, down 5%",
      "driver": "Apple Watch Series 10"
    },
    {
      "segment": "Services",
      "performance": "26.6 billion, up 12%",
      "driver": "All-time revenue record"
    }
  ],
  "explicit_risks": [
    {
      "risk": "Tariff impacts on costs",
      "time_horizon": "unspecified"
    }
  ],
  "capital_allocation": {
    "buybacks": "25 billion",
    "dividends": "3.8 billion",
    "debt_activity": "increased commercial paper by 4 billion",
    "m_and_a": "not disclosed"
  },
  "causal_claims": [
    {
      "claim": "Tariffs estimated to add $900 million to costs",
      "type": "L1_association",
      "evidence_reference": "Management commentary"
    }
  ],
  "quantifiable_surprises": [
    {
      "metric": "Revenue",
      "expected": "not disclosed",
      "actual": "95.4 billion",
      "surprise": "not disclosed"
    }
  ],
  "high_signal_summary": [
    "Revenue of $95.4 billion, up 5% YoY.",
    "EPS of $1.65, up 8% YoY.",
    "iPhone revenue at $46.8 billion, up 2%.",
    "Mac revenue at $7.9 billion, up 7%.",
    "iPad revenue at $6.4 billion, up 15%.",
    "Wearables revenue at $7.5 billion, down 5%.",
    "Services revenue at $26.6 billion, up 12%.",
    "Gross margin at 47.1%.",
    "Operating cash flow of $24 billion.",
    "Returned $29 billion to shareholders.",
    "Authorized additional $100 billion for share repurchases.",
    "Raised dividend by 4% to $0.26 per share."
  ]
}