{
  "metadata": {
    "ticker": "AAPL",
    "year": "2025",
    "quarter": "Q3",
    "news_item_count": 565
  },
  "macro_news": [
    {
      "headline_theme": "US-EU Trade Deal",
      "relevance_to_company": "Potentially eases tariff concerns for US companies including Apple.",
      "sentiment": "positive"
    },
    {
      "headline_theme": "US Tariffs on India",
      "relevance_to_company": "New tariffs could impact Apple's manufacturing costs in India.",
      "sentiment": "negative"
    },
    {
      "headline_theme": "AI Market Competition",
      "relevance_to_company": "Growing competition in AI could affect Apple's market position.",
      "sentiment": "mixed"
    }
  ],
  "company_specific_news": [
    {
      "headline_theme": "iPhone 17 Launch",
      "event_type": "product",
      "sentiment": "positive"
    },
    {
      "headline_theme": "Retail Store Closure in China",
      "event_type": "other",
      "sentiment": "negative"
    },
    {
      "headline_theme": "Antitrust Lawsuit from Elon Musk",
      "event_type": "regulatory",
      "sentiment": "negative"
    },
    {
      "headline_theme": "JPMorgan Credit Card Deal",
      "event_type": "merger",
      "sentiment": "positive"
    },
    {
      "headline_theme": "AI Strategy Concerns",
      "event_type": "other",
      "sentiment": "negative"
    },
    {
      "headline_theme": "Strong iPhone Sales",
      "event_type": "earnings_preview",
      "sentiment": "positive"
    },
    {
      "headline_theme": "Antitrust Probe in Spain",
      "event_type": "regulatory",
      "sentiment": "negative"
    },
    {
      "headline_theme": "Apple's Investment in US Manufacturing",
      "event_type": "other",
      "sentiment": "positive"
    }
  ],
  "aggregate_news_signal": {
    "overall_sentiment": "mixed",
    "dominant_theme": "Product launches and regulatory challenges",
    "conflicting_signals": true
  }
}