{
  "schema_version": "asset_state_v2",
  "ticker": "XOM",
  "year": 2024,
  "quarter": "Q2",
  "as_of": "2024-06-30",
  "features": {
    "close": 108.54,
    "ret_20d": 0.0099,
    "ret_60d": -0.0272,
    "ret_120d": 0.1413,
    "ret_252d": 0.1307,
    "vol_20d": 0.2217,
    "vol_60d": 0.1837,
    "vol_120d": 0.1816,
    "downside_vol_60d": 0.1115,
    "drawdown_60d": -0.1061,
    "max_drawdown_1y": -0.1873,
    "sma_20d": 106.19,
    "sma_50d": 108.62,
    "sma_200d": 101.69,
    "momentum_200d": 1.0673,
    "momentum_12_1": 0.116,
    "idiosyncratic_momentum": -0.0429,
    "trend_consistency": 0.4833,
    "sharpe_60d": -0.6304,
    "beta_1y": 0.2471,
    "size_log_mcap": null,
    "value_book_to_market": null,
    "avg_dollar_volume_20d": 1989140747.01,
    "gross_margin": null,
    "roe": null,
    "free_cash_flow_yield": null,
    "debt_to_equity": null,
    "earnings_surprise_pct": -0.0463
  }
}